ice_estimation/__init__.py
ice_estimation/filters.py
ice_estimation-1.0.0.dist-info/LICENSE
ice_estimation-1.0.0.dist-info/METADATA
ice_estimation-1.0.0.dist-info/WHEEL
ice_estimation-1.0.0.dist-info/top_level.txt
ice_estimation-1.0.0.dist-info/RECORD
